{"cookies": [{"name": "csrftoken", "value": "fzB7BBqKnXeGFSlu2Pb8Vv", "domain": ".instagram.com", "path": "/", "expires": 1811433109.228952, "httpOnly": false, "secure": true, "sameSite": "Lax"}, {"name": "datr", "value": "Ke7oaaJgSF3soRYYrio21WS2", "domain": ".instagram.com", "path": "/", "expires": 1811433001.292157, "httpOnly": true, "secure": true, "sameSite": "None"}, {"name": "ig_did", "value": "C293AF2F-EF4F-47EA-BBC7-463ABB9738FC", "domain": ".instagram.com", "path": "/", "expires": 1808409001.2922, "httpOnly": true, "secure": true, "sameSite": "None"}, {"name": "mid", "value": "aejuKQALAAF47N91VHlQOiYwNOly", "domain": ".instagram.com", "path": "/", "expires": 1811433001.292237, "httpOnly": true, "secure": true, "sameSite": "None"}, {"name": "wd", "value": "1280x720", "domain": ".instagram.com", "path": "/", "expires": 1777477906, "httpOnly": false, "secure": true, "sameSite": "Lax"}, {"name": "ds_user_id", "value": "79978656966", "domain": ".instagram.com", "path": "/", "expires": 1784649109.229182, "httpOnly": false, "secure": true, "sameSite": "None"}, {"name": "sessionid", "value": "79978656966%3ANFvrwl5H5VX95r%3A26%3AAYgSvqBzg5haF9dqR6gBNAKaWVspXlZeJqDk7GcfdA", "domain": ".instagram.com", "path": "/", "expires": 1808409105.455195, "httpOnly": true, "secure": true, "sameSite": "None"}, {"name": "ps_l", "value": "1", "domain": ".instagram.com", "path": "/", "expires": 1811433105.85216, "httpOnly": true, "secure": true, "sameSite": "Lax"}, {"name": "ps_n", "value": "1", "domain": ".instagram.com", "path": "/", "expires": 1811433105.852286, "httpOnly": true, "secure": true, "sameSite": "None"}, {"name": "rur", "value": "\"GTN\\05479978656966\\0541808409109:01fe7ad937fa2da73e4c874d3211bc84da1a3f7a5c7978fbcf4aa20f44c695f6e6e1562e\"", "domain": ".instagram.com", "path": "/", "expires": -1, "httpOnly": true, "secure": true, "sameSite": "Lax"}], "origins": [{"origin": "https://www.instagram.com", "localStorage": [{"name": "chatd-deviceid", "value": "e8bd257a-7970-49b1-984b-33af181b8eb6"}, {"name": "hb_timestamp", "value": "1776873032287"}, {"name": "IGSession", "value": "e31eas:1776874937157"}, {"name": "pigeon_state", "value": "{\"lastDeviceInfoTime\":0}"}, {"name": "pixel_fire_ts", "value": "1776873107179"}, {"name": "signal_flush_timestamp", "value": "1776873002312"}, {"name": "Session", "value": "gjiepn:1776873172157"}, {"name": "ig_boost_on_web_campaign_upsell_shown", "value": "false"}, {"name": "banzai:last_storage_flush", "value": "1776873002997.5"}, {"name": "caa_feta_onetap_users_migrated", "value": "true"}]}]}